{
	"class" : {
		 },
	"instance" : {
		"glBindTextureUnit:with:" : "TZ 5/11/2020 16:01",
		"glBlitNamedFramebuffer:with:with:with:with:with:with:with:with:with:with:with:" : "TZ 5/11/2020 16:01",
		"glCheckNamedFramebufferStatus:with:" : "TZ 5/11/2020 16:01",
		"glClearNamedBufferData:with:with:with:with:" : "TZ 5/11/2020 16:01",
		"glClearNamedBufferSubData:with:with:with:with:with:with:" : "TZ 5/11/2020 16:01",
		"glClearNamedFramebufferfi:with:with:with:with:" : "TZ 5/11/2020 16:01",
		"glClearNamedFramebufferfv:with:with:with:" : "TZ 5/11/2020 16:01",
		"glClearNamedFramebufferiv:with:with:with:" : "TZ 5/11/2020 16:01",
		"glClearNamedFramebufferuiv:with:with:with:" : "TZ 5/11/2020 16:01",
		"glClipControl:with:" : "TZ 5/11/2020 16:01",
		"glCompressedTextureSubImage1D:with:with:with:with:with:with:" : "TZ 5/11/2020 16:01",
		"glCompressedTextureSubImage2D:with:with:with:with:with:with:with:with:" : "TZ 5/11/2020 16:01",
		"glCompressedTextureSubImage3D:with:with:with:with:with:with:with:with:with:with:" : "TZ 5/11/2020 16:01",
		"glCopyNamedBufferSubData:with:with:with:with:" : "TZ 5/11/2020 16:01",
		"glCopyTextureSubImage1D:with:with:with:with:with:" : "TZ 5/11/2020 16:01",
		"glCopyTextureSubImage2D:with:with:with:with:with:with:with:" : "TZ 5/11/2020 16:01",
		"glCopyTextureSubImage3D:with:with:with:with:with:with:with:with:" : "TZ 5/11/2020 16:01",
		"glCreateBuffers:with:" : "TZ 5/11/2020 16:01",
		"glCreateFramebuffers:with:" : "TZ 5/11/2020 16:01",
		"glCreateProgramPipelines:with:" : "TZ 5/11/2020 16:01",
		"glCreateQueries:with:with:" : "TZ 5/11/2020 16:01",
		"glCreateRenderbuffers:with:" : "TZ 5/11/2020 16:01",
		"glCreateSamplers:with:" : "TZ 5/11/2020 16:01",
		"glCreateTextures:with:with:" : "TZ 5/11/2020 16:01",
		"glCreateTransformFeedbacks:with:" : "TZ 5/11/2020 16:01",
		"glCreateVertexArrays:with:" : "TZ 5/11/2020 16:01",
		"glDisableVertexArrayAttrib:with:" : "TZ 5/11/2020 16:01",
		"glEnableVertexArrayAttrib:with:" : "TZ 5/11/2020 16:01",
		"glFlushMappedNamedBufferRange:with:with:" : "TZ 5/11/2020 16:01",
		"glGenerateTextureMipmap:" : "TZ 5/11/2020 16:01",
		"glGetCompressedTextureImage:with:with:with:" : "TZ 5/11/2020 16:01",
		"glGetCompressedTextureSubImage:with:with:with:with:with:with:with:with:with:" : "TZ 5/11/2020 16:01",
		"glGetGraphicsResetStatus" : "TZ 5/11/2020 16:01",
		"glGetNamedBufferParameteri64v:with:with:" : "TZ 5/11/2020 16:01",
		"glGetNamedBufferParameteriv:with:with:" : "TZ 5/11/2020 16:01",
		"glGetNamedBufferPointerv:with:with:" : "TZ 5/11/2020 16:01",
		"glGetNamedBufferSubData:with:with:with:" : "TZ 5/11/2020 16:01",
		"glGetNamedFramebufferAttachmentParameteriv:with:with:with:" : "TZ 5/11/2020 16:01",
		"glGetNamedFramebufferParameteriv:with:with:" : "TZ 5/11/2020 16:01",
		"glGetNamedRenderbufferParameteriv:with:with:" : "TZ 5/11/2020 16:01",
		"glGetQueryBufferObjecti64v:with:with:with:" : "TZ 5/11/2020 16:01",
		"glGetQueryBufferObjectiv:with:with:with:" : "TZ 5/11/2020 16:01",
		"glGetQueryBufferObjectui64v:with:with:with:" : "TZ 5/11/2020 16:01",
		"glGetQueryBufferObjectuiv:with:with:with:" : "TZ 5/11/2020 16:01",
		"glGetTextureImage:with:with:with:with:with:" : "TZ 5/11/2020 16:01",
		"glGetTextureLevelParameterfv:with:with:with:" : "TZ 5/11/2020 16:01",
		"glGetTextureLevelParameteriv:with:with:with:" : "TZ 5/11/2020 16:01",
		"glGetTextureParameterIiv:with:with:" : "TZ 5/11/2020 16:01",
		"glGetTextureParameterIuiv:with:with:" : "TZ 5/11/2020 16:01",
		"glGetTextureParameterfv:with:with:" : "TZ 5/11/2020 16:01",
		"glGetTextureParameteriv:with:with:" : "TZ 5/11/2020 16:01",
		"glGetTextureSubImage:with:with:with:with:with:with:with:with:with:with:with:" : "TZ 5/11/2020 16:01",
		"glGetTransformFeedbacki64_v:with:with:with:" : "TZ 5/11/2020 16:01",
		"glGetTransformFeedbacki_v:with:with:with:" : "TZ 5/11/2020 16:01",
		"glGetTransformFeedbackiv:with:with:" : "TZ 5/11/2020 16:01",
		"glGetVertexArrayIndexed64iv:with:with:with:" : "TZ 5/11/2020 16:01",
		"glGetVertexArrayIndexediv:with:with:with:" : "TZ 5/11/2020 16:01",
		"glGetVertexArrayiv:with:with:" : "TZ 5/11/2020 16:01",
		"glGetnColorTable:with:with:with:with:" : "TZ 5/11/2020 16:01",
		"glGetnCompressedTexImage:with:with:with:" : "TZ 5/11/2020 16:01",
		"glGetnConvolutionFilter:with:with:with:with:" : "TZ 5/11/2020 16:01",
		"glGetnHistogram:with:with:with:with:with:" : "TZ 5/11/2020 16:01",
		"glGetnMapdv:with:with:with:" : "TZ 5/11/2020 16:01",
		"glGetnMapfv:with:with:with:" : "TZ 5/11/2020 16:01",
		"glGetnMapiv:with:with:with:" : "TZ 5/11/2020 16:01",
		"glGetnMinmax:with:with:with:with:with:" : "TZ 5/11/2020 16:01",
		"glGetnPixelMapfv:with:with:" : "TZ 5/11/2020 16:01",
		"glGetnPixelMapuiv:with:with:" : "TZ 5/11/2020 16:01",
		"glGetnPixelMapusv:with:with:" : "TZ 5/11/2020 16:01",
		"glGetnPolygonStipple:with:" : "TZ 5/11/2020 16:01",
		"glGetnSeparableFilter:with:with:with:with:with:with:with:" : "TZ 5/11/2020 16:01",
		"glGetnTexImage:with:with:with:with:with:" : "TZ 5/11/2020 16:01",
		"glGetnUniformdv:with:with:with:" : "TZ 5/11/2020 16:01",
		"glGetnUniformfv:with:with:with:" : "TZ 5/11/2020 16:01",
		"glGetnUniformiv:with:with:with:" : "TZ 5/11/2020 16:01",
		"glGetnUniformuiv:with:with:with:" : "TZ 5/11/2020 16:01",
		"glInvalidateNamedFramebufferData:with:with:" : "TZ 5/11/2020 16:01",
		"glInvalidateNamedFramebufferSubData:with:with:with:with:with:with:" : "TZ 5/11/2020 16:01",
		"glMapNamedBuffer:with:" : "TZ 5/11/2020 16:01",
		"glMapNamedBufferRange:with:with:with:" : "TZ 5/11/2020 16:01",
		"glMemoryBarrierByRegion:" : "TZ 5/11/2020 16:01",
		"glNamedBufferData:with:with:with:" : "TZ 5/11/2020 16:01",
		"glNamedBufferStorage:with:with:with:" : "TZ 5/11/2020 16:01",
		"glNamedBufferSubData:with:with:with:" : "TZ 5/11/2020 16:01",
		"glNamedFramebufferDrawBuffer:with:" : "TZ 5/11/2020 16:01",
		"glNamedFramebufferDrawBuffers:with:with:" : "TZ 5/11/2020 16:01",
		"glNamedFramebufferParameteri:with:with:" : "TZ 5/11/2020 16:01",
		"glNamedFramebufferReadBuffer:with:" : "TZ 5/11/2020 16:01",
		"glNamedFramebufferRenderbuffer:with:with:with:" : "TZ 5/11/2020 16:01",
		"glNamedFramebufferTexture:with:with:with:" : "TZ 5/11/2020 16:01",
		"glNamedFramebufferTextureLayer:with:with:with:with:" : "TZ 5/11/2020 16:01",
		"glNamedRenderbufferStorage:with:with:with:" : "TZ 5/11/2020 16:01",
		"glNamedRenderbufferStorageMultisample:with:with:with:with:" : "TZ 5/11/2020 16:01",
		"glReadnPixels:with:with:with:with:with:with:with:" : "TZ 5/11/2020 16:01",
		"glTextureBarrier" : "TZ 5/11/2020 16:01",
		"glTextureBuffer:with:with:" : "TZ 5/11/2020 16:01",
		"glTextureBufferRange:with:with:with:with:" : "TZ 5/11/2020 16:01",
		"glTextureParameterIiv:with:with:" : "TZ 5/11/2020 16:01",
		"glTextureParameterIuiv:with:with:" : "TZ 5/11/2020 16:01",
		"glTextureParameterf:with:with:" : "TZ 5/11/2020 16:01",
		"glTextureParameterfv:with:with:" : "TZ 5/11/2020 16:01",
		"glTextureParameteri:with:with:" : "TZ 5/11/2020 16:01",
		"glTextureParameteriv:with:with:" : "TZ 5/11/2020 16:01",
		"glTextureStorage1D:with:with:with:" : "TZ 5/11/2020 16:01",
		"glTextureStorage2D:with:with:with:with:" : "TZ 5/11/2020 16:01",
		"glTextureStorage2DMultisample:with:with:with:with:with:" : "TZ 5/11/2020 16:01",
		"glTextureStorage3D:with:with:with:with:with:" : "TZ 5/11/2020 16:01",
		"glTextureStorage3DMultisample:with:with:with:with:with:with:" : "TZ 5/11/2020 16:01",
		"glTextureSubImage1D:with:with:with:with:with:with:" : "TZ 5/11/2020 16:01",
		"glTextureSubImage2D:with:with:with:with:with:with:with:with:" : "TZ 5/11/2020 16:01",
		"glTextureSubImage3D:with:with:with:with:with:with:with:with:with:with:" : "TZ 5/11/2020 16:01",
		"glTransformFeedbackBufferBase:with:with:" : "TZ 5/11/2020 16:01",
		"glTransformFeedbackBufferRange:with:with:with:with:" : "TZ 5/11/2020 16:01",
		"glUnmapNamedBuffer:" : "TZ 5/11/2020 16:01",
		"glVertexArrayAttribBinding:with:with:" : "TZ 5/11/2020 16:01",
		"glVertexArrayAttribFormat:with:with:with:with:with:" : "TZ 5/11/2020 16:01",
		"glVertexArrayAttribIFormat:with:with:with:with:" : "TZ 5/11/2020 16:01",
		"glVertexArrayAttribLFormat:with:with:with:with:" : "TZ 5/11/2020 16:01",
		"glVertexArrayBindingDivisor:with:with:" : "TZ 5/11/2020 16:01",
		"glVertexArrayElementBuffer:with:" : "TZ 5/11/2020 16:01",
		"glVertexArrayVertexBuffer:with:with:with:with:" : "TZ 5/11/2020 16:01",
		"glVertexArrayVertexBuffers:with:with:with:with:with:" : "TZ 5/11/2020 16:01" } }
